atar/__init__.py
atar/cli.py
atar-1.0.15.dist-info/licenses/LICENSE
src/__init__.py
src/Utilities/__init__.py
src/Utilities/features.py
src/Utilities/flexMenu.py
src/Utilities/log.py
src/Utilities/modelTrain.py
src/Utilities/modelValid.py
src/Utilities/rTrain.py
src/Utilities/roboFlowDataSet.py
src/Utilities/sDetect.py
src/Utilities/vDetect.py
atar-1.0.15.dist-info/METADATA
atar-1.0.15.dist-info/WHEEL
atar-1.0.15.dist-info/entry_points.txt
atar-1.0.15.dist-info/top_level.txt
atar-1.0.15.dist-info/RECORD
