Metadata-Version: 2.4
Name: atar
Version: 1.0.15
Summary: A CLI tool for AI tasks such as dataset handling, training, and validation.
Home-page: https://github.com/otman-dev/atar-cli
Author: MOUHIB Otman
Author-email: mouhib.otm@gmail.com
Classifier: Programming Language :: Python :: 3
Classifier: License :: OSI Approved :: MIT License
Classifier: Operating System :: OS Independent
Requires-Python: >=3.6
License-File: LICENSE
Requires-Dist: ultralytics
Requires-Dist: roboflow
Requires-Dist: supervision
Dynamic: author
Dynamic: author-email
Dynamic: classifier
Dynamic: description
Dynamic: description-content-type
Dynamic: home-page
Dynamic: license-file
Dynamic: requires-dist
Dynamic: requires-python
Dynamic: summary
